dal/dao.py
database/hawqalDB.sqlite
hawqal/__init__.py
hawqal/cities.py
hawqal/citiesbycountry.py
hawqal/country.py
hawqal/states.py
hawqal_python-0.1.5.8.dist-info/LICENSE
hawqal_python-0.1.5.8.dist-info/METADATA
hawqal_python-0.1.5.8.dist-info/WHEEL
hawqal_python-0.1.5.8.dist-info/top_level.txt
hawqal_python-0.1.5.8.dist-info/RECORD
