Metadata-Version: 2.1
Name: hawqal-python
Version: 0.1.5.8
Summary: Python package that contains the data of world's countries,states and their cities name
Home-page: https://github.com/CapregSoft/Hawqal-python.git
Author: Husnain Khurshid
Author-email: muhammadhusnainkh@gmail.com
Keywords: husnain khurshid,capregsoft,hawqal,world data,states
Classifier: Development Status :: 1 - Planning
Classifier: Intended Audience :: Developers
Classifier: Programming Language :: Python :: 3
Classifier: Operating System :: Unix
Classifier: Operating System :: MacOS :: MacOS X
Classifier: Operating System :: Microsoft :: Windows
License-File: LICENSE
